shopant_sdk/__init__.py
shopant_sdk/requests_helper.py
shopant_sdk/server.py
shopant_sdk-0.0.3.dist-info/METADATA
shopant_sdk-0.0.3.dist-info/WHEEL
shopant_sdk-0.0.3.dist-info/top_level.txt
shopant_sdk-0.0.3.dist-info/RECORD
