Metadata-Version: 2.1
Name: shopant-sdk
Version: 0.0.3
Summary: ShopAnt SDK
Home-page: https://github.com/anyant/shopant-sdk
Author: guyskk
Author-email: guyskk@qq.com
License: UNKNOWN
Platform: UNKNOWN
Classifier: Development Status :: 3 - Alpha
Classifier: Intended Audience :: Developers
Classifier: Topic :: Software Development :: Build Tools
Classifier: License :: OSI Approved :: MIT License
Classifier: Programming Language :: Python :: 3
Classifier: Programming Language :: Python :: 3.5
Classifier: Programming Language :: Python :: 3.6
Classifier: Programming Language :: Python :: 3.7
Classifier: Programming Language :: Python :: 3.8
Classifier: Programming Language :: Python :: 3 :: Only
Requires-Python: >=3.5
Requires-Dist: requests
Requires-Dist: pyjwt
Provides-Extra: dev
Requires-Dist: pytest ; extra == 'dev'
